cyberfusion/SyncSupport/__init__.py
cyberfusion/SyncSupport/exceptions.py
cyberfusion/SyncSupport/unix_users.py
python3_cyberfusion_sync_support-1.4.dist-info/METADATA
python3_cyberfusion_sync_support-1.4.dist-info/WHEEL
python3_cyberfusion_sync_support-1.4.dist-info/top_level.txt
python3_cyberfusion_sync_support-1.4.dist-info/RECORD
