Metadata-Version: 2.4
Name: python3-cyberfusion-sync-support
Version: 1.4
Summary: Library for syncing objects (e.g. directories).
Author-email: Cyberfusion <support@cyberfusion.io>
Project-URL: Source, https://github.com/CyberfusionIO/python3-cyberfusion-sync-support
Requires-Dist: python3-cyberfusion-common~=2.12
